tableschema_elasticsearch/VERSION
tableschema_elasticsearch/__init__.py
tableschema_elasticsearch/mappers.py
tableschema_elasticsearch/storage.py
tableschema_elasticsearch-2.1.4.dist-info/LICENSE.md
tableschema_elasticsearch-2.1.4.dist-info/METADATA
tableschema_elasticsearch-2.1.4.dist-info/WHEEL
tableschema_elasticsearch-2.1.4.dist-info/top_level.txt
tableschema_elasticsearch-2.1.4.dist-info/RECORD
