Metadata-Version: 2.1
Name: tableschema-elasticsearch
Version: 2.1.4
Summary: Generate ES Indexes, load and extract data, based on JSON Table Schema descriptors.
Home-page: https://github.com/frictionlessdata/tableschema-elasticsearch-py
Author: Open Knowledge Foundation
Author-email: info@okfn.org
License: MIT
Keywords: frictionless data
Platform: UNKNOWN
Classifier: Development Status :: 4 - Beta
Classifier: Environment :: Web Environment
Classifier: Intended Audience :: Developers
Classifier: License :: OSI Approved :: MIT License
Classifier: Operating System :: OS Independent
Classifier: Programming Language :: Python :: 2
Classifier: Programming Language :: Python :: 2.7
Classifier: Programming Language :: Python :: 3
Classifier: Programming Language :: Python :: 3.5
Classifier: Programming Language :: Python :: 3.6
Classifier: Topic :: Internet :: WWW/HTTP :: Dynamic Content
Classifier: Topic :: Software Development :: Libraries :: Python Modules
Requires-Dist: six>=1.9
Requires-Dist: elasticsearch<9.0,>=7.0
Provides-Extra: develop
Requires-Dist: coverage; extra == "develop"
Requires-Dist: mock; extra == "develop"
Requires-Dist: pylama; extra == "develop"
Requires-Dist: pytest; extra == "develop"
Requires-Dist: pytest-cov; extra == "develop"
Requires-Dist: tabulator; extra == "develop"
Requires-Dist: tox; extra == "develop"
Requires-Dist: setuptools==71.0.0; extra == "develop"
Requires-Dist: python-dotenv; extra == "develop"
